zlogger/__init__.py
zlogger/client.py
zlogger_client-1.0.5.dist-info/METADATA
zlogger_client-1.0.5.dist-info/WHEEL
zlogger_client-1.0.5.dist-info/top_level.txt
zlogger_client-1.0.5.dist-info/RECORD
