Metadata-Version: 2.4
Name: zlogger-client
Version: 1.0.5
Summary: Python client for Zlogger logging service
Home-page: https://github.com/your-username/zlogger-python
Author: Zlogger Team
Author-email: Zlogger Team <info@zlogger.ch>
License: MIT
Project-URL: Homepage, https://zlogger.ch
Project-URL: Repository, https://github.com/zurd46/zlogger
Requires-Python: >=3.7
Requires-Dist: requests>=2.31.0
Dynamic: author
Dynamic: home-page
Dynamic: requires-python
